{
  "title": "退職代行を使う前に確認すべき5つのチェックポイント2026",
  "content": "# 退職代行を使う前に確認すべき5つのチェックポイント2026\n\n退職代行サービスは「明日から会社に行きたくない」という切迫した状況で利用を検討するケースが多く、勢いで申込んでしまった結果、想定外の追加費用や手続き漏れに直面する人が後を絶ちません。本記事では、2026年現時点で公開されている公的情報と実務上のトラブル事例をふまえて、契約前に必ず確認すべき5つのチェックポイントを段階順に整理します。読み物として完結する形でまとめており、特定業者の紹介や紹介リンクは含みません。\n\n## ✅ チェック1：業者の種別と「交渉権」の有無\n\n退職代行サービスは大きく **弁護士型 / 労働組合型 / 民間業者型** の3タイプに分かれるとされています。同じ「退職代行」という名前でも、できることが法的に異なる点が最大のポイントです。\n\n| 種別 | 退職意思の伝達 | 給与・有給の交渉 | 紛争対応 | 料金相場 |\n|------|---------------|-----------------|---------|---------|\n| 弁護士型 | ✅ | ✅ | ✅ | 5万〜10万円台が中心 |\n| 労働組合型 | ✅ | ✅（団体交渉権） | △ | 2万〜3万円台が中心 |\n| 民間業者型 | ✅ | ❌（伝達のみ） | ❌ | 1万〜3万円台が中心 |\n\n民間業者型は「会社に退職する旨を伝える」ところまでしか対応できないとされており、未払い残業代の請求や有給消化日数の交渉が必要になるケースには本来不向きです。自分の状況で交渉が発生しそうかどうかを最初に判定してください。\n\n## ✅ チェック2：料金体系と「追加費用が出る場面」\n\n公式サイトに掲載されている基本料金だけを見て契約すると、後から追加費用を請求されてトラブルになるケースが報告されています。確認すべきは以下の4点です。\n\n1. **基本料金に含まれる範囲**：会社への連絡回数に上限があるか\n2. **追加費用の発生条件**：会社から「親に連絡する」と言われた等のイレギュラー対応で別料金になるか\n3. **キャンセルポリシー**：申込後に会社と話せた等で利用を取りやめた場合の返金ルール\n4. **後払い・分割の可否**：給与支給日まで支払いを待ってもらえるか\n\n「追加費用一切なし」を明記している業者でも、規約の細部に「ただし以下の場合を除く」という除外条項が入っているケースがあるため、契約前に規約全文に目を通すことをおすすめします。\n\n## ✅ チェック3：有給消化と離職票の取り扱い\n\n退職代行を依頼するときに見落とされやすいのが「退職後の手続き」です。特に以下の2点は失業保険受給や次の職場での社会保険手続きに直結します。\n\n- **有給休暇の消化交渉**：労働基準法上、有給は労働者の権利ですが、消化日数や時期の調整は事実上の交渉事項になります。民間業者型では交渉できないとされているため、有給を完全消化したい場合は労働組合型または弁護士型を選ぶ必要があります。\n- **離職票の発行催促**：失業保険を受給するには会社から離職票を受け取ることが必須です。退職代行業者が「退職後の離職票発行を会社にフォローするか」を契約前に確認してください。\n\n> 💡 ポイント：離職票は退職日から10日前後で会社が発行する建付けですが、退職代行を経由した場合は会社側の対応が遅れがちなケースが報告されています。発行が遅延した場合の連絡窓口を業者と決めておくと安心です。\n\n## ✅ チェック4：書面合意（合意書・退職届）の扱い\n\n退職代行を経由した退職でも、後々の証拠として **書面で合意内容を残す** ことが重要とされています。最低限残しておきたい書類は次の3つです。\n\n1. **退職届のコピー**：退職日と退職理由を本人名義で記載したもの\n2. **合意書（必要な場合）**：有給消化日数・最終給与・退職金の支払日について合意した文書\n3. **会社とのやり取りログ**：業者が会社と交わしたメール/通話記録の写し\n\n民間業者型は法的代理権を持たないため、合意書の作成サポートは原則として弁護士型・労働組合型での対応になります。書面なしで口頭合意のみで進めると、後から「そんな話は聞いていない」と覆されるリスクがあるとされています。\n\n## ✅ チェック5：自分の精神状態と「相談先」のセカンドオピニオン\n\n最後のチェックポイントは、利用する自分自身の状態確認です。退職代行を検討する状況の多くは、心身ともに消耗していることが想定されます。契約前に以下のセカンドオピニオン窓口を一度は通しておくことをおすすめします。\n\n- **総合労働相談コーナー（厚生労働省）**：全国の労働局・労基署内に設置されており、無料で相談可能とされています\n- **法テラス**：弁護士費用が払えない場合の収入要件付き支援制度あり\n- **自治体の労政事務所・労働相談窓口**：地域によって名称は異なりますが、無料相談を提供しているケースが多いです\n\nこれらの公的窓口に1度相談することで、「そもそも退職代行を使わずに直接交渉できる」「労基署案件として動いた方が良い」といった代替ルートが見えるケースもあるとされています。\n\n## 🧭 5つのチェックポイントまとめ\n\n| # | チェック項目 | 確認するタイミング |\n|---|------------|------------------|\n| 1 | 業者の種別と交渉権 | 業者選定時 |\n| 2 | 料金体系と追加費用 | 契約直前 |\n| 3 | 有給消化と離職票 | 契約時 |\n| 4 | 書面合意の扱い | 退職前後 |\n| 5 | 精神状態と公的相談窓口 | 検討開始時 |\n\n5つのチェックすべてに「想定どおり」と答えられる状態に整えてから契約に進めれば、退職代行利用後のトラブル発生率を大きく下げられるとされています。\n\n## ❓ FAQ\n\n### Q1: 退職代行は本当に当日連絡だけで辞められますか？\n\n民間業者・労働組合・弁護士いずれの形態でも、依頼当日に会社へ連絡する運用自体は可能とされています。ただし「辞められる」と「即日トラブルなく退職完了する」は別物です。会社側が即日退職を拒否したり、退職日を1〜2週間後に設定するよう求めるケースもあるため、即日での連絡は可能でも実質的な退職完了には数日〜2週間程度かかるケースが多いと考えておくと安全です。\n\n### Q2: 民間業者と弁護士、どちらを選ぶべきですか？\n\n未払い残業代・有給消化日数・退職金などの「金銭交渉」が発生しそうな場合は弁護士型または労働組合型が無難とされています。一方で、会社にトラブル要素がなく単に「自分の口から退職を伝えたくない」だけのケースであれば、民間業者型でも目的は達成できる可能性が高いです。自分のケースが交渉込みかどうかをチェック1で判定してから選ぶ流れが安全です。\n\n### Q3: 退職代行を使うと転職で不利になりますか？\n\n退職代行を利用したという事実そのものが転職活動で不利に扱われる仕組みは、2026年現時点で確認されていません。前職への問い合わせは原則として在籍確認止まりとされており、退職経緯まで踏み込んで聞かれるケースは多くないとされています。むしろ退職を引き延ばして体調を崩す方が、その後の転職活動に与える影響が大きいケースもあるため、必要であれば前向きに利用を検討してください。\n\n---\n\n退職は人生の節目です。勢いで決めず、5つのチェックポイントを一度紙に書き出して整理してから業者と契約に進むと、後から後悔するパターンを大きく減らせるとされています。\n\n<script type=\"application/ld+json\">{\"@context\": \"https://schema.org\", \"@type\": \"BreadcrumbList\", \"itemListElement\": [{\"@type\": \"ListItem\", \"position\": 1, \"name\": \"ホーム\", \"item\": \"https://musclelove-777.github.io/taishoku-navi/\"}, {\"@type\": \"ListItem\", \"position\": 2, \"name\": \"退職代行の選び方\", \"item\": \"https://musclelove-777.github.io/taishoku-navi/category/退職代行の選び方.html\"}, {\"@type\": \"ListItem\", \"position\": 3, \"name\": \"退職代行を使う前に確認すべき5つのチェックポイント2026\", \"item\": \"https://musclelove-777.github.io/taishoku-navi/articles/2026-04-29-taishoku-daiko-5-checkpoints-before-use.html\"}]}</script>\n",
  "meta_description": "退職代行サービスの利用前に必ず確認したい5つのチェックポイントを実務目線で解説。業者種別・料金・有給・離職票・書面合意までを段階的にチェック。",
  "description": "退職代行サービスの利用前に必ず確認したい5つのチェックポイントを実務目線で解説。業者種別・料金・有給・離職票・書面合意までを段階的にチェック。",
  "tags": [
    "退職代行",
    "退職代行 チェックポイント",
    "退職代行 注意点",
    "退職前確認",
    "2026"
  ],
  "slug": "2026-04-29-taishoku-daiko-5-checkpoints-before-use",
  "hero_emoji": "🧭",
  "hero_gradient": "135deg",
  "image_search_query": "退職代行を使う前に確認すべき5つのチェックポイント2026",
  "content_image_count": 0,
  "keyword": "退職代行を使う前に確認すべきチェックポイント",
  "category": "退職代行の選び方",
  "date": "2026-04-29",
  "generated_at": "2026-04-29T08:24:30.541125",
  "has_affiliate": false,
  "affiliate_count": 0,
  "char_count": 3214
}